jam/__init__.py
jam/admin.py
jam/apps.py
jam/exporter.py
jam/generator.py
jam/models.py
jam/tests.py
jam/utils.py
jam/views.py
jam/migrations/__init__.py
django_json_api_model-0.0.5.dist-info/METADATA
django_json_api_model-0.0.5.dist-info/WHEEL
django_json_api_model-0.0.5.dist-info/top_level.txt
django_json_api_model-0.0.5.dist-info/RECORD
