Metadata-Version: 2.1
Name: django-json-api-model
Version: 0.0.5
Summary: UNKNOWN
Home-page: https://github.com/uptick/django-jam
Author: Luke Hodkinson
Author-email: luke.hodkinson@uptickhq.com
Maintainer: Uptick
Maintainer-email: dev@uptickhq.com
License: BSD
Platform: UNKNOWN
Classifier: Development Status :: 3 - Alpha
Classifier: Framework :: Django
Classifier: Intended Audience :: Developers
Classifier: License :: OSI Approved :: BSD License
Classifier: Natural Language :: English
Classifier: Operating System :: OS Independent
Classifier: Programming Language :: Python
Requires-Dist: setuptools
Requires-Dist: inflection
